nivis/__init__.py
nivis/exception.py
nivis/execution.py
nivis/interpreter.py
nivis/lexer.py
nivis/mathmatics.py
nivis/parsers.py
nivis/type.py
nivis/Grammar/Token
nivis/Lib/IOStream/__init__.nivis
nivis/Modules/asyncio/__init__.py
nivis-0.1.1a1.dist-info/METADATA
nivis-0.1.1a1.dist-info/WHEEL
nivis-0.1.1a1.dist-info/licenses/COPYING
nivis-0.1.1a1.dist-info/RECORD
