Metadata-Version: 2.1
Name: nivis
Version: 0.1.1a1
Summary: Python implementation for Nivis.
Author-email: 简律纯 <i@jyunko.cn>
License: MIT
License-File: COPYING
Requires-Python: >=3.11
Requires-Dist: ply>=3.11
